vision_agents/plugins/krisp/__init__.py
vision_agents/plugins/krisp/turn_detection.py
vision_agents_plugins_krisp-0.1.14.dist-info/METADATA
vision_agents_plugins_krisp-0.1.14.dist-info/WHEEL
vision_agents_plugins_krisp-0.1.14.dist-info/RECORD
