Metadata-Version: 2.4
Name: vision-agents-plugins-krisp
Version: 0.1.14
Summary: Krisp turn detection plugin for Vision Agents
Project-URL: Documentation, https://visionagents.ai/
Project-URL: Website, https://visionagents.ai/
Project-URL: Source, https://github.com/GetStream/Vision-Agents
License-Expression: Apache-2.0
Keywords: AI,agents,krisp,turn detection,voice agents
Requires-Python: >=3.10
Requires-Dist: numpy>=1.24.0
Requires-Dist: vision-agents>=0.1.0
